mini_worker/__init__.py
mini_worker/base_worker.py
mini_worker/cli.py
mini_worker/manager.py
mini_worker/monitoring.py
mini_worker/utils.py
mini_worker-0.1.1.dist-info/licenses/LICENSE
mini_worker-0.1.1.dist-info/METADATA
mini_worker-0.1.1.dist-info/WHEEL
mini_worker-0.1.1.dist-info/entry_points.txt
mini_worker-0.1.1.dist-info/top_level.txt
mini_worker-0.1.1.dist-info/RECORD
