Metadata-Version: 2.4
Name: mini-worker
Version: 0.1.1
Summary: A simple, parameter-driven worker framework with internal loops and file-based monitoring
Home-page: https://github.com/yourusername/mini-worker
Author: Your Name
Author-email: Michael Chen <xychen@msn.com>
License: MIT
Project-URL: Homepage, https://github.com/xychenmsn/mini-worker
Project-URL: Repository, https://github.com/xychenmsn/mini-worker
Project-URL: Issues, https://github.com/xychenmsn/mini-worker/issues
Classifier: Development Status :: 3 - Alpha
Classifier: Intended Audience :: Developers
Classifier: License :: OSI Approved :: MIT License
Classifier: Operating System :: OS Independent
Classifier: Programming Language :: Python :: 3
Classifier: Programming Language :: Python :: 3.8
Classifier: Programming Language :: Python :: 3.9
Classifier: Programming Language :: Python :: 3.10
Classifier: Programming Language :: Python :: 3.11
Classifier: Programming Language :: Python :: 3.12
Classifier: Topic :: Software Development :: Libraries :: Python Modules
Classifier: Topic :: System :: Distributed Computing
Requires-Python: >=3.8
License-File: LICENSE
Requires-Dist: click>=8.0.0
Requires-Dist: psutil>=5.8.0
Provides-Extra: dev
Requires-Dist: pytest>=6.0; extra == "dev"
Requires-Dist: pytest-cov; extra == "dev"
Requires-Dist: black; extra == "dev"
Requires-Dist: flake8; extra == "dev"
Requires-Dist: mypy; extra == "dev"
Dynamic: author
Dynamic: home-page
Dynamic: license-file
Dynamic: requires-python
